SandboxAdapter/Converter.py
SandboxAdapter/Core.py
SandboxAdapter/__init__.py
SandboxAdapter/static/index.html
erispulse_sandboxadapter-1.0.4.dist-info/licenses/LICENSE
erispulse_sandboxadapter-1.0.4.dist-info/METADATA
erispulse_sandboxadapter-1.0.4.dist-info/WHEEL
erispulse_sandboxadapter-1.0.4.dist-info/entry_points.txt
erispulse_sandboxadapter-1.0.4.dist-info/top_level.txt
erispulse_sandboxadapter-1.0.4.dist-info/RECORD
