Metadata-Version: 2.4
Name: ErisPulse-SandboxAdapter
Version: 1.0.4
Summary: ErisPulse的沙箱适配器，提供网页界面用于调试和模拟消息
Author: ErisPulse Team
License: MIT License
Project-URL: homepage, https://github.com/ErisPulse/ErisPulse-SandboxAdapter
Requires-Python: >=3.10
License-File: LICENSE
Dynamic: license-file
